turtlegridutil/__init__.py
turtlegridutil/core.py
turtlegridutil-0.1.0.dist-info/LICENSE
turtlegridutil-0.1.0.dist-info/METADATA
turtlegridutil-0.1.0.dist-info/WHEEL
turtlegridutil-0.1.0.dist-info/RECORD
