Metadata-Version: 2.3
Name: turtlegridutil
Version: 0.1.0
Summary: The utility for drawing coordinate grid on python turtle's screen.
License: MIT
Author: Vasyl Boliukh
Author-email: vskesha@gmail.com
Requires-Python: >=3.8
Classifier: License :: OSI Approved :: MIT License
Classifier: Programming Language :: Python :: 3
Classifier: Programming Language :: Python :: 3.8
Classifier: Programming Language :: Python :: 3.9
Classifier: Programming Language :: Python :: 3.10
Classifier: Programming Language :: Python :: 3.11
Classifier: Programming Language :: Python :: 3.12
Classifier: Programming Language :: Python :: 3.13
